<flat-profile>
<Station_Name>{$display_name_1}</Station_Name>
<Profile_Rule>http://{$domain_name}{$project_path}/app/provision/?mac=$MA</Profile_Rule>
<Resync_Periodic>0</Resync_Periodic>
<Primary_NTP_Server>pool.ntp.org</Primary_NTP_Server>
<Upgrade_Rule></Upgrade_Rule>
<Voice_Mail_Number>*97</Voice_Mail_Number>
<Time_Zone>GMT{$time_zone_offset}</Time_Zone>
<Daylight_Saving_Time_Rule>start=9/27/0/2;end=4/4/0/3;save=0</Daylight_Saving_Time_Rule>
<Blind_Attn-Xfer_Enable_1_>No</Blind_Attn-Xfer_Enable_1_>
<Proxy_1_>{$server_address_1}</Proxy_1_>
<Display_Name_1_>{$display_name_1}</Display_Name_1_>
<User_ID_1_>{$user_id_1}</User_ID_1_>
<Password_1_>{$user_password_1}</Password_1_>
<Use_Auth_ID_1_>No</Use_Auth_ID_1_>
<Preferred_Codec_1_>G711u</Preferred_Codec_1_>
<Proxy_2_>{$server_address_2}</Proxy_2_>
<Display_Name_2_>{$display_name_2}</Display_Name_2_>
<User_ID_2_>{$user_id_2}</User_ID_2_>
<Password_2_>{$user_password_2}</Password_2_>
<Use_Auth_ID_2_>No</Use_Auth_ID_2_>
<Preferred_Codec_2_>G711u</Preferred_Codec_2_>
<Dial_Plan_1_>
(*xxxxxxx|*xxxxxx|*xxxxx|*xxxx|*xxx|*xx*|*x|**xxxxx|**xxxx|**xxx|**xx|[3469]11|0|00|[2-9]xxxxxx|1xxx[2-9]xxxxxxS0|xxxxxxxxxxxx.)
</Dial_Plan_1_>
<Headset_Input_Gain>6</Headset_Input_Gain>
<Time_Format>24hr</Time_Format>
<Date_Format>day/month</Date_Format>
</flat-profile>